alignak_checks_monitoring/__init__.py
alignak_checks_monitoring-1.1.4.data/data/share/alignak/etc/arbiter/packs/monitoring/commands.cfg
alignak_checks_monitoring-1.1.4.data/data/share/alignak/etc/arbiter/packs/monitoring/services.cfg
alignak_checks_monitoring-1.1.4.data/data/share/alignak/etc/arbiter/packs/monitoring/templates.cfg
alignak_checks_monitoring-1.1.4.data/data/share/alignak/etc/arbiter/packs/resource.d/monitoring.cfg
alignak_checks_monitoring-1.1.4.data/data/share/alignak/etc/backend-json/monitoring/commands.json
alignak_checks_monitoring-1.1.4.data/data/share/alignak/etc/backend-json/monitoring/hosts-templates.json
alignak_checks_monitoring-1.1.4.data/data/share/alignak/etc/backend-json/monitoring/services-templates.json
alignak_checks_monitoring-1.1.4.data/data/share/alignak/etc/backend-json/monitoring/setup.sh
alignak_checks_monitoring-1.1.4.dist-info/AUTHORS
alignak_checks_monitoring-1.1.4.dist-info/LICENSE
alignak_checks_monitoring-1.1.4.dist-info/METADATA
alignak_checks_monitoring-1.1.4.dist-info/WHEEL
alignak_checks_monitoring-1.1.4.dist-info/top_level.txt
alignak_checks_monitoring-1.1.4.dist-info/RECORD
